spankins/__init__.py
spankins/scripts/diagnose.groovy
spankins/scripts/ping.groovy
spankins/templates/add-master.groovy
spankins/templates/set-agent-port.groovy
spankins-0.0.10.dist-info/METADATA
spankins-0.0.10.dist-info/RECORD
spankins-0.0.10.dist-info/WHEEL
spankins-0.0.10.dist-info/entry_points.txt
spankins-0.0.10.dist-info/top_level.txt
