Metadata-Version: 2.1
Name: spankins
Version: 0.0.10
Summary: UNKNOWN
Home-page: https://github.com/jamesalbert/spankins
Author: jamesrobertalbert@gmail.com
Author-email: UNKNOWN
License: UNKNOWN
Platform: UNKNOWN
Classifier: Programming Language :: Python :: 3
Classifier: License :: OSI Approved :: GNU General Public License (GPL)
Requires-Dist: docopt
Requires-Dist: requests
Requires-Dist: jinja2
